monti/__init__.py
monti/monti.py
monti/montiutils.py
monti-1.2.2.dist-info/LICENSE
monti-1.2.2.dist-info/METADATA
monti-1.2.2.dist-info/WHEEL
monti-1.2.2.dist-info/top_level.txt
monti-1.2.2.dist-info/RECORD
