Metadata-Version: 2.1
Name: monti
Version: 1.2.2
Summary: A multi-omics integrative analysis tool
Home-page: https://github.com/inukj/MONTI
Author: Inuk Jung
Author-email: inukjung@gmail.com
License: UNKNOWN
Platform: UNKNOWN
Classifier: Programming Language :: Python :: 3
Classifier: License :: OSI Approved :: MIT License
Classifier: Operating System :: OS Independent
Requires-Python: >=3.6
License-File: LICENSE
